netflow/__init__.py
netflow/analyzer.py
netflow/collector.py
netflow/ipfix.py
netflow/utils.py
netflow/v1.py
netflow/v5.py
netflow/v9.py
netflow-0.12.1.dist-info/LICENSE
netflow-0.12.1.dist-info/METADATA
netflow-0.12.1.dist-info/WHEEL
netflow-0.12.1.dist-info/top_level.txt
netflow-0.12.1.dist-info/RECORD
