Metadata-Version: 2.1
Name: netflow
Version: 0.12.1
Summary: NetFlow v1, v5, v9 and IPFIX tool suite implemented in Python 3
Home-page: https://github.com/bitkeks/python-netflow-v9-softflowd
Author: Dominik Pataky
Author-email: software+pynetflow@dpataky.eu
License: MIT
Keywords: netflow ipfix collector parser
Classifier: Programming Language :: Python :: 3
Classifier: License :: OSI Approved :: MIT License
Classifier: Intended Audience :: Developers
Classifier: Intended Audience :: System Administrators
Requires-Python: >=3.5.3
License-File: LICENSE
